gym_info/__init__.py
gym_info/api.py
gym_info/discretization/__init__.py
gym_info/discretization/core.py
gym_info/discretization/envs.py
gym_info/discretization/trajectory.py
gym_info/measures/__init__.py
gym_info/measures/histogram.py
gym_info/presets/__init__.py
gym_info/presets/classic_control.py
gym_info/report/__init__.py
gym_info/report/models.py
gym_info/report/style.py
gym_info/report/text.py
gym_info/wrappers/__init__.py
gym_info/wrappers/info_wrapper.py
gym_info-0.1.1.dist-info/METADATA
gym_info-0.1.1.dist-info/WHEEL
gym_info-0.1.1.dist-info/licenses/LICENSE
gym_info-0.1.1.dist-info/RECORD
