Metadata-Version: 2.4
Name: gym_info
Version: 0.1.1
Summary: Information-theoretic metrics for Gymnasium environments
Author-email: Rafael Stutz Pereira Martins <rafaelstutz14@gmail.com>
License-File: LICENSE
Requires-Python: >=3.10
Requires-Dist: gymnasium>=1.2.2
Requires-Dist: matplotlib>=3.10.7
Requires-Dist: numpy>=1.24
Requires-Dist: pandas>=2.3.3
